{"page_content": "STEEL DYNAMICS | SUSTAINABILITY REPORT 1\nCEO Letter\nDifferentiated Model \nValuing People Valuing StakeholdersValuing the Environment Governing Principles |\n01 |\n02 |03 |\n04 |\n05 |TABLE OF\nCONTENTS\nAbout this report\nThis report was developed in part to  \nshare our long-standing commitment, \ndedication, and achievements regarding sustainability. Based on stakeholder feedback concerning the most beneficial methods to disclose certain related information, we have provided metrics using the Global Reporting Initiative (GRI) and the Sustainability  \nAccounting Standards Board\u2019s (SASB)  \nIron & Steel Producers Standard.  GRI provides a framework for organizations to report on the impact and management of economic, social, and environmental matters. SASB provides a framework to report on industry-specific sustainability topics that are deemed to be material. Additionally, in order to make our information more accessible, we have provided a GRI and SASB cross-reference index, and it is available on our website at steeldynamics.com under Sustainability.", "metadata": {"source": "NASDAQ_STLD_2019.pdf", "page": 1, "parser": "pypdf", "split_method": "page", "run_time": "2024-05-29 08:35:04"}, "type": "Document"}