{"page_content": "NASDAQ: LSCC -15\nGlobal Workforce OverviewEurope\nRegionGlobal\nUS Workforce\nRace / EthnicityGender ** Location\n\u00a7We are proud of our dedicated and \nloyal workforce \n\u00a7The average tenure of a Lattice employee \nis 8.3 years\n** Includes 25% Female Board \nof Directors Members & 25% \nFemale Executive Leaders\nAsiaMale\nWhiteAsianFemale\nURM*AmericaOUR PEOPLE\n*Under -Represented Minorities", "metadata": {"source": "NASDAQ_LSCC_2020.pdf", "page": 14, "parser": "pypdf", "split_method": "page", "run_time": "2024-05-29 08:35:04"}, "type": "Document"}