{"page_content": "inclusivefamilyexcellent\nevolvingawesomediversegood\nflexible\nteamworkconnected\ntransparentcommittedchanging\ngreatinnovativerespectful\ncollaborative\nfriendlywelcoming\ntrust\ndedicatedfairamazing\nopenprogressive\nIn 2022, Veradigm continued its focus on \nlistening to and learning from associates\u2019 \nviews of the company culture. Associates \nmost often choose words such as inclusive, \ncollaborative, diverse, friendly, and family  \nto describe the culture. Veradigm takes \ngreat pride in how associates view the \nculture today, and we believe there are \nalways opportunities for growth.\nInsightful Impact\n6", "metadata": {"source": "NASDAQ_MDRX_2022.pdf", "page": 7, "parser": "pypdf", "split_method": "page", "run_time": "2024-05-29 08:35:04"}, "type": "Document"}