{"page_content": "632020 Inaugural ESG Report\nInternal mobility 2020\nEmployees promoted internally 106\nPercentage of female  \nemployees promoted54Engagement survey \nparticipation rate32019 2020\nPercentage 95 86< 25 years old 24 - 40 years old\n Female Male\n41 - 55 years old\n > 55 years old\nEmeryville Leland\nRemote CA\n Remote non-CA\n2018\n1272019\n972020\n106\nGENDER\nAGE\nLOCATION55%15%\n74%14%9%9%\n60%24%7%\n51%\nAsian Black or African American\nHispanic or Latino\nWhite Two or more races\nDeclined to answerPaci\ufb01c Islander< 25 years old 24 - 40 years old\n Female Male\n41 - 55 years old\n > 55 years old\nGENDER\nAGE\nRACE49%4%4%4%\n31%\n48%\n7%4%\n1%53%32%11%\n51%Employee hires\nDiversity of employees\n3: More information on the survey can be found in Chapter 3", "metadata": {"source": "NASDAQ_AMRS_2020.pdf", "page": 62, "parser": "pypdf", "split_method": "page", "run_time": "2024-05-29 08:35:04"}, "type": "Document"}