{"page_content": "Reporting Approach World Class Governance Corporate Citizenship Care for Our Environment Overview Our Response to COVID -19\nEmergency Response Management TeamRisk Management \u2013Business Continuity Plan\n40 \u00a9 2022 AerCap  | Confidential property of the company, not for disclosure or use without permission\uf07dAerCap\u2019s Business Continuity Plan deals with \neight major business disruption events. It involves multiple levels of management and departments\n\uf07dThe plan is available internally to all employees\n\uf07dWe also use scenario analyses to prepare employees with structured responses upon occurrence of these unlikely events\nOther than COVID -19, \nthere were no major \nbusiness disruption \nevents in 20210\n NORMAL \nSITUATION\nEMERGENCY \nSTAGE\nFALLBACK\nSTAGE\nBusiness Continuity StagesEmergency Officer \nGEC Member\n(Leader)Member of the GEC \nor Designee \n(Deputy Leaders)\nGroup Chief \nInformation Officer \nand Facilities \n(Member)Head of Human \nResources\n(Member)Head of Corporate \nCommunications\n(Support)Head of Investor \nRelations\n(Member)\nFunctional Departments\nRECOVERY\nSTAGE", "metadata": {"source": "NASDAQ_AER_2021.pdf", "page": 40, "parser": "pypdf", "split_method": "page", "run_time": "2024-05-29 08:35:04"}, "type": "Document"}