{"page_content": "Create change.  \nOur mission \u2014 to Change the World Through Digital Experiences \u2014  \nis relevant both in the midst of crisis and in the best of times.  \nWe remain committed to using the power of creativity to change the \nworld \u2014 by championing our employees, empowering every voice, \nlifting our communities, and building a sustainable future. \nadobe.co m/createchange\nDesigned by Studio Rainwater", "metadata": {"source": "NASDAQ_ADBE_2022.pdf", "page": 44, "parser": "pypdf", "split_method": "page", "run_time": "2024-05-29 08:35:04"}, "type": "Document"}