{"page_content": "Page 68\nCorporate Social Responsibility ReportEnergy Efficient SemiconductorsAppendix\nList of Acronyms\n3TG Tantalum, tin, tungsten and gold\n8D \u201c8 disciplines\u201d of problem solving \nACEEE American Council for an Energy-Efficient Economy \nADAS Adaptive Driver Assistance Systems\nAPAC Asia-Pacific\nBack-End, assembly \ntest or subcon (BE)Manufacturing facility that produces finished product \nin the package and testing services \nBEL Business Ethics Liaison\nCEO Chief Executive Officer\nCFSI Conflict Free Sourcing Initiative\nCSR Corporate Social Responsibility\nCOO Chief Operating Officer\nD&I Diversity and Inclusion \nDJSI Dow Jones Sustainability Indices\nDMAIC Define, Measure, Analyze, Improve and Control\nDRC Democratic Republic of the Congo\nEHS Environmental Health and Safety\nEMEA Europe, Middle East and Africa\nERM Enterprise Risk Management\nEuP European Energy Using Products\nEVP Employee Volunteer Program\nFront-End (FE),  \nfab or foundryRefers to anything that is processing on a full wafer \nGCG Global Corporate Giving\nGDPR General Data Protection Regulation \nGEO Global Educational Opportunities\nGHG Greenhouse Gases\nGRI Global Reporting Initiative\nHCCA Health Care Compliance Association\nIoT Internet of Things\nISMF Manufacturing site located in Seremban, Malaysia\nISO International Organization for Standardization\nKPI Key Performance Indicator\nL&D Learning and Development\nLSS Lean Six Sigma \nMTCE Metric tons of carbon equivalent NBRI National Business Research Institute\nOHSASOccupational Health and Safety Assessment Series \n(OHSAS 18001)\nOECDOrganisation for Economic Co-operation and \nDevelopment\nONSC Manufacturing site located in Shenzhen, China\nONSZ Manufacturing site located in Suzhou, China\nOSPI Manufacturing site located in Cebu, Philippines\nOSV Manufacturing site located in Bien Hoa, Vietnam\nPAC Political Action Committee\nPpb Parts Per Billion\nPFCs Perfluorinated Compounds\nR&D Research and Development \nRBA Responsible Business Alliance\nREACHRegistration, Evaluation and Authorization of \nChemicals\nRMAP Responsible Minerals Assurance Process\nRMI Responsible Minerals Initiative\nRoHS Restriction of Hazardous Substances\nSAQ Self-Assessment Questionnaire\nSCCE Society of Corporate Compliance and Ethics\nSDGs Sustainable Development Goals\nSEC Securities and Exchange Commission\nSECs Solutions Engineering Centers\nSIA Semiconductor Industry Association\nSiPM Silicon Photomultipliers\nSoC Systems on Chip\nSPAD Single Photon Avalanche Diode\nSTEAM Science, Technology, Engineering, Arts, Mathematics \nSTEM UPScience, Technology, Engineering and Mathematics \nfor Under-represented Populations\nUN United Nations\nUNGC United Nations Global Compact \nVAP Validated Assessment Program\nWME World\u2019s Most Ethical Company\nWSC World Semiconductor Council", "metadata": {"source": "N6LEV9~G.pdf", "page": 67, "parser": "pypdf", "split_method": "page", "run_time": "2024-05-29 08:35:04"}, "type": "Document"}