{"page_content": "02\nFY22 IMPACT REPORT   OVERVIEW \nENERGY & MATERIALS\nHEALTH & RESILIENCE\nWORK & PROSPERITY\nGOVERNANCE\nAPPENDIX \nContents\nEnergy & Materials\nImprove our operations\nDriving net-zero carbon emissions\nOur carbon footprint Partner with customersArchitecture, Engineering & Construction Design & ManufacturingMedia & EntertainmentAdvance industries Catalyze innovationAccelerate collaborationShape policiesOverview\nA message from our President and CEO  \nFY22 highl\nights\nOur companyOur impact strategyPhilanthropyHealth & Resilience\nImprove our operations\nResilience and well\n-\nbeing\nEmployee health and safety\nPartner with customersArchitecture, Engineering & Construction Design & ManufacturingMedia & EntertainmentAdvance industries Catalyze innovationAccelerate collaborationShape policies\nAppendix  \nImpact strategy assessments\nData summary\nSustainability-enabling solutionsUnited Nations Global Compact index\nUnited Nations Sustainable Development Goals index\nSustainability Accounting Standards Board indexEndnotesGovernance\nCorporate governance \nCompany strategy\nAccountabilityTrustPrivacy and data security  Ethics and compliance  Human rightsSuppliers and business partners Public policyWork & Prosperity\nImprove our operations\nCompany culture\nFlexible workplaceLearning and organization developmentEmployee impact at workDiversity and belongingPartner with customersEducationIndustry trendsArchitecture, Engineering & ConstructionDesign & ManufacturingMedia & Entertainment Advance industries Catalyze innovationAccelerate collaborationShape policies\nPerformance data included in this report is based on the Autodesk fiscal year when noted, and the calendar year otherwise. The Autodesk 2022 fiscal year ran from February 1, 2021, through January 31, 2022.  \nPerformance data covers Autodesk\u2019s global operations, unless otherwise stated. In some cases, segments in tables do not add up to the total due to rounding. Dashes indicate where data was unavailable. All dollar amounts listed are in USD.", "metadata": {"source": "NASDAQ_ADSK_2022.pdf", "page": 1, "parser": "pypdf", "split_method": "page", "run_time": "2024-05-29 08:35:04"}, "type": "Document"}