{"page_content": "A M E D I S Y S  2 0 2 1  E S G  R E P O R T    |    1 6F O R W A R D - L O O K I N G\nS T A T E M E N T S\nT h i s  r e p o r t  d o e s  n o t  c o v e r  a l l  i n f o r m a t i o n  a b o u t  o u r  b u s i n e s s .  R e f e r e n c e s  i n  t h i s  r e p o r t  t o  i n f o r m a t i o n  s h o u l d  n o t  b e\nc o n s t r u e d  a s  a  c h a r a c t e r i z a t i o n  r e g a r d i n g  t h e  m a t e r i a l i t y  o f  s u c h  i n f o r m a t i o n  t o  o u r  f i n a n c i a l  r e s u l t s  o r  f o r  p u r p o s e s\no f  t h e  U . S .  s e c u r i t i e s  l a w s .  T h e  i n f o r m a t i o n  c o v e r e d  b y  t h i s  r e p o r t  c o n t a i n s  f o r w a r d - l o o k i n g  s t a t e m e n t s  w i t h i n  t h e\nm e a n i n g  o f  t h e  P r i v a t e  S e c u r i t i e s  L i t i g a t i o n  R e f o r m  A c t  o f  1 9 9 5 ,  i n c l u d i n g  s t a t e m e n t s  r e g a r d i n g  o u r  E S G  f r a m e w o r k ,\ni n c l u d i n g  g o a l s ,  c o m m i t m e n t s ,  a n d  s t r a t e g i e s  a n d  r e l a t e d  b u s i n e s s  a n d  s t a k e h o l d e r  i m p a c t s .  T h e s e  s t a t e m e n t s  i n v o l v e\nr i s k s  a n d  u n c e r t a i n t i e s ,  a n d  a c t u a l  r e s u l t s  m a y  d i f f e r  m a t e r i a l l y  f r o m  a n y  f u t u r e  r e s u l t s  e x p r e s s e d  o r  i m p l i e d  b y  t h e\nf o r w a r d - l o o k i n g  s t a t e m e n t s ,  i n c l u d i n g  a n y  f a i l u r e  t o  m e e t  s t a t e d  g o a l s  a n d  c o m m i t m e n t s  i n  o u r  E S G  f r a m e w o r k ,  a n d\ne x e c u t e  o u r  s t r a t e g i e s  i n  t h e  t i m e  f r a m e  e x p e c t e d  o r  a t  a l l ,  a s  a  r e s u l t  o f  m a n y  f a c t o r s ,  i n c l u d i n g  c h a n g i n g  g o v e r n m e n t\nr e g u l a t i o n s ,  c o n t i n u e d  u n c e r t a i n t y  r e g a r d i n g  t h e  e x t e n t  a n d  d u r a t i o n  o f  t h e  i m p a c t  o f  t h e  C O V I D - 1 9  p a n d e m i c  a n d\nt h e  r e s p o n s e s  o f  g o v e r n m e n t  a n d  p r i v a t e  i n d u s t r y  t h e r e t o .\nM o r e  i n f o r m a t i o n  o n  r i s k s ,  u n c e r t a i n t i e s ,  a n d  o t h e r  p o t e n t i a l  f a c t o r s  t h a t  c o u l d  a f f e c t  o u r  b u s i n e s s  a n d  p e r f o r m a n c e\ni s  i n c l u d e d  i n  o u r  f i l i n g s  w i t h  t h e  S E C ,  i n c l u d i n g  i n  t h e  \u201c R i s k  F a c t o r s \u201d  a n d  \u201c M a n a g e m e n t \u2019 s  D i s c u s s i o n  a n d  A n a l y s i s  o f\nF i n a n c i a l  C o n d i t i o n  a n d  R e s u l t s  o f  O p e r a t i o n s \u201d  s e c t i o n s  o f  A m e d i s y s '  m o s t  r e c e n t l y  f i l e d  p e r i o d i c  r e p o r t s  o n  F o r m\n1 0 - K  a n d  F o r m  1 0 - Q  a n d  s u b s e q u e n t  f i l i n g s .  F o r w a r d - l o o k i n g  s t a t e m e n t s  s p e a k  o n l y  a s  o f  t h e  d a t e  t h e  s t a t e m e n t s  a r e\nm a d e  a n d  a r e  b a s e d  o n  i n f o r m a t i o n  a v a i l a b l e  t o  A m e d i s y s  a t  t h e  t i m e  t h o s e  s t a t e m e n t s  a r e  m a d e  a n d / o r\nm a n a g e m e n t \u2019 s  g o o d  f a i t h  b e l i e f  a s  o f  t h a t  t i m e  w i t h  r e s p e c t  t o  f u t u r e  e v e n t s .  A m e d i s y s  a s s u m e s  n o  o b l i g a t i o n  t o\nu p d a t e  f o r w a r d - l o o k i n g  s t a t e m e n t s  t o  r e f l e c t  e v e n t s  o r  c i r c u m s t a n c e s  a f t e r  t h e  d a t e  t h e y  w e r e  m a d e ,  e x c e p t  a s\nr e q u i r e d  b y  l a w", "metadata": {"source": "NASDAQ_AMED_2021.pdf", "page": 15, "parser": "pypdf", "split_method": "page", "run_time": "2024-05-29 08:35:04"}, "type": "Document"}