{"page_content": "Sustainability Report 202134For the fourth year, Applied Materials was given \nthe Excellence Employer award by China\u2019s #1 jobs \nboard, 51Job, recognizing our achievements in \ndiversity and inclusion. \u201cApplied Materials constantly seeks ways to \nimprove as a company. Whether it\u2019s addressing \nenvironmental and sustainability challenges, \nshrinking gender equity discrepancies, or \npromoting a more inclusive workplace, these \nefforts make me love working at a global \ncompany that listens to employees and leverages \nthe various talents and diverse backgrounds that \nmake up Applied\u2019s culture.\u201d\nHadley\nSales Account ManagerRecruiting and Hiring \nin Challenging Times\nThroughout 2021, we adapted and expanded \nour recruiting, hiring and onboarding \npractices for a challenging labor and work \nenvironment. Our efforts included:\n > Applied New Hire Experience. As part \nof our MY HR portal, we introduced a \nvirtual onboarding process that orients \nnew hires to our values, mission, \nbusiness organization, locations and \nother essentials, all via modules and \nnotifications that promote better \nengagement and information retention. \nThe system coordinates with the \nemployee\u2019s manager and a new-hire \nbuddy, simplifying and standardizing \nthe onboarding process.  > New College Graduate Rotation \nPrograms. To drive in-depth, cross-\nfunctional training, provide access \nto a global knowledge database and \nassure optimal placement of new hires, \ninternal organizations including Supply \nChain, Finance (Austin and Silicon \nValley), and Implant (Gloucester) \noffered rotation programs that \nincluded mentoring, networking, skills \ndevelopment and hands-on experience \nacross various areas of their operation. \n > Virtual Internships. In North America \nand globally, our virtual internship \nprograms continued giving students \nexposure to our diverse and inclusive \nworkplace and introducing them \nto career paths and roles in both \nengineering and corporate. In the U.S., \nwe hired a total of 143 interns, 53% of \nwhom were female.\n > China New Star Program. Spanning  \n12 Applied locations in China, this  \nNCG program saw 13% female new \nhires in 2021.\nINTRODUCTION  \nPURPOSE \nPEOPLE \nRecruiting and Hiring \nOur Culture of Inclusion \nLearning and Development \nEmployee Safety and  \nSupport During COVID-19 \nOccupational Health  \nand Safety \nHuman Rights \nPLANET \nPROGRESS", "metadata": {"source": "NASDAQ_AMAT_2021.pdf", "page": 33, "parser": "pypdf", "split_method": "page", "run_time": "2024-05-29 08:35:04"}, "type": "Document"}