{"page_content": "FY2019 GLOBAL CITIZENSHIP ANNUAL REPORT\nSTAKEHOLDER ENGAGEMENT0123  \nEach year, we solicit feedback from \nour customers and business partners \nto shape our Global Citizenship \nprogram plans and strategies. For \nexample, through a variety of surveys \nand reporting initiatives, Seagate \nshares detailed information about the \ncompany\u2019s environmental performance \nand greenhouse gas emissions to help \nthe electronics industry improve its \nenvironmental footprint. We also solicit \nfeedback through Net Promoter Score \nand Customer Scorecards (quarterly \nbusiness reviews) data quarterly. We meet regularly with investors, \ngovernments, nongovernmental \norganizations, local communities, and \nother civil society members to gather \nperspectives about trends in business \nand society that may influence not \nonly our business success, but also \nthe extent to which we can contribute \npositively to sustainable development. \nWe constantly engage with employees, \nand for suppliers we have a dedicated \nsupplier day, webinars, training and more. STAKEHOLDER ENGAGEMENT\nEngaging with key stakeholders on relevant environmental, social and \ngovernance issues is an important activity that provides Seagate with \nthe insights and relationships needed to make well-informed business \ndecisions. Seagate identifies stakeholders through a mapping exercise \nthat utilizes a set of criteria to prioritize engagement. The criteria \nincluded past engagement, collaboration with industry association  \ne.g. the RBA, and publication of industry reports, among others.\nBACK TO CONTENTS", "metadata": {"source": "NASDAQ_STX_2019.pdf", "page": 122, "parser": "pypdf", "split_method": "page", "run_time": "2024-05-29 08:35:04"}, "type": "Document"}