{"page_content": " 11\nSUSTAINABILITY\nMONDEL\u0112Z INTERNATIONAL PROGRESS REPORT | 2017\nCocoa\nCocoa Life  is our long-term $400 million USD \ncommitment to create a vibrant cocoa supply \nchain, while transforming the lives of cocoa \nfarmers and communities at scale. \nCocoa sustainability is in our DNA and the DNA \nof our brands. Since launching in 2012, Cocoa Life  \nhas focused on achieving scale and driving impact \nin key cocoa producing countries: Ghana, C\u00f4te \nd\u2019Ivoire, Indonesia, Dominican Republic, India \nand Brazil. Our goal is to reach 200,000 farmers \nand one million community members by 2022, \nand ultimately source all of our cocoa sustainably, \nmainly through Cocoa Life .Cocoa Life  is based on three non-negotiable \nprinciples: it is holistic and farmer-centered, \ncommitted to partnership and aligned with our \nsourcing. Its holistic approach drives change \nand addresses diverse challenges in cocoa \nfarming communities. Since the challenges are \ninterrelated, the solution needs to be as well. Our \nefforts center around five focus areas: Farming, \nCommunity, Livelihoods, Youth and Environment. \nAdditionally, we have three themes that cut across \nthese five key areas: women\u2019s empowerment, \nchild labor and climate change.Cocoa Life  links cocoa farming \nwith community development. \nBeyond social and economic \nchallenges, communities are \nfacing environmental difficulties. \nThe program includes a wide \narray of initiatives to support local communities, \nhelping them to cultivate stronger, more \nresilient crops; fight deforestation and reduce \nenvironmental impact; and create real change \nacross our cocoa communities. \nCocoa Life  connects the beginning and end of the \ncocoa supply chain, from the farmers who grow the \ncocoa to the consumers who enjoy our chocolate.  \nYOUTH LIVELIHOODS FARMING ENVIRONMENT COMMUNITYHOW COCOA LIFE WORKS\nCocoa Life  is driving change in five key areas , as well as cross-cutting themes of women\u2019s empowerment, elimination of child labor and climate change.\nCocoa Life  tracks and reports impact against 10 global KPIs  that correspond to the program\u2019s five key areas.", "metadata": {"source": "NASDAQ_MDLZ_2017.pdf", "page": 10, "parser": "pypdf", "split_method": "page", "run_time": "2024-05-29 08:35:04"}, "type": "Document"}