{"page_content": "This report includes forward-looking statements and estimates of future performance that may differ from actual results because of \nuncertainties and risks encountered in day-to-day business.2022 Corporate Responsibility and Sustainability Report\nSustainability Snapshot \nSafe, reliable, affordable and sustainable energy powers our communities. By growing our use of \nclean energy, advancing energy efficiency and electrifying transportation, we can meet our goal of deep carbon reductions by 2030 and net-zero carbon electricity by 2050.", "metadata": {"source": "NASDAQ_MGEE_2022.pdf", "page": 0, "parser": "pypdf", "split_method": "page", "run_time": "2024-05-29 08:35:04"}, "type": "Document"}