{"page_content": "akamai.com    |   1\n akamai.com    |   1Table of Contents\nLetter from the CEO 2\nLetter from the Chief ESG Officer 3\nThe Akamai Foundation 4\nEnvironmental sustainability 6\nInclusion, diversity, and engagement 8\nEthics and compliance  10\nHuman rights  11\nResponsible supply chain 11\nData privacy 12\nData security and cybersecurity 13\nWellness 14\nMateriality assessment 15\nAkamai\u2019s awards and accolades 15", "metadata": {"source": "NASDAQ_AKAM_2021.pdf", "page": 1, "parser": "pypdf", "split_method": "page", "run_time": "2024-05-29 08:35:04"}, "type": "Document"}