{"page_content": "91 \n \n [Public]  \nMarkham  5 <1 1 1 1 \nSanta Clara    n/a <1 <1 <1 <1 \nSunnyvale  1 n/a n/a n/a n/a \nSingapore  <1 <1 <1 <1 <1 \nHW Recycled/Reused (metric tons)  1 <1 <1 1 <1 \nHW Treated Off -Site (metric tons)  <1 <1 <1 <1 1 \nHW Incinerated (metric tons)  6 1 1 <1 1 \nHW Landfilled (metric tons)  1 1 1 1 2 \nTotal Waste Generated \n(NHW+HW)(metric tons)  666 643 697 491 455 \nTotal Waste Generated per Revenue \n(g/$USD)  0.12  0.10  0.10  0.05  0.03  \nContract Manufacturing HW Generated \n(metric tons)71 12,156  14,310  21,512  30,725  54,343  \n      \nWastewater       \nTotal Wastewater Discharge72 (million \nliters)  22 9 10 4 3 \nAustin  8 9 10 4 3 \nSunnyvale  14 n/a n/a n/a n/a \nWastewater generated per Revenue \n(ML/$)  4.17  1.45  1.52  0.42  0.17  \n       \nAir Emissions73      \nOzone Depleting Substances (MTCO2e)  2,548  2,099  2,019  962 1,579  \n       \nCompliance       \nNumber of Environmental Non -\nCompliances  1 0 0 0 0 \nFines (USD)  0 0 0 0 0 \n \n  \n \n72 AMD generates a limited amount of wastewater that requires treatment by the municipal wastewater treatment plant, in \naccordance with water quality permi tting.  \n73 Fugitive emissions from refrigerant use are included as part of total scope 1 emissions.  \n ", "metadata": {"source": "NASDAQ_AMD_2022.pdf", "page": 90, "parser": "pypdf", "split_method": "page", "run_time": "2024-05-29 08:35:04"}, "type": "Document"}